polywrap_wasm/__init__.py
polywrap_wasm/buffer.py
polywrap_wasm/constants.py
polywrap_wasm/errors.py
polywrap_wasm/exports.py
polywrap_wasm/imports/__init__.py
polywrap_wasm/imports/abort.py
polywrap_wasm/imports/debug.py
polywrap_wasm/imports/env.py
polywrap_wasm/imports/get_implementations.py
polywrap_wasm/imports/invoke.py
polywrap_wasm/imports/subinvoke.py
polywrap_wasm/imports/types/__init__.py
polywrap_wasm/imports/types/base_wrap_imports.py
polywrap_wasm/imports/wrap_imports.py
polywrap_wasm/inmemory_file_reader.py
polywrap_wasm/instance.py
polywrap_wasm/linker/__init__.py
polywrap_wasm/linker/abort.py
polywrap_wasm/linker/debug.py
polywrap_wasm/linker/env.py
polywrap_wasm/linker/get_implementations.py
polywrap_wasm/linker/invoke.py
polywrap_wasm/linker/subinvoke.py
polywrap_wasm/linker/subinvoke_implementation.py
polywrap_wasm/linker/types/__init__.py
polywrap_wasm/linker/types/base_wrap_linker.py
polywrap_wasm/linker/wrap_linker.py
polywrap_wasm/memory.py
polywrap_wasm/py.typed
polywrap_wasm/types/__init__.py
polywrap_wasm/types/invoke_result.py
polywrap_wasm/types/state.py
polywrap_wasm/types/wasm_invoke_options.py
polywrap_wasm/wasm_package.py
polywrap_wasm/wasm_wrapper.py
polywrap_wasm-0.1.2.dist-info/METADATA
polywrap_wasm-0.1.2.dist-info/WHEEL
polywrap_wasm-0.1.2.dist-info/RECORD
