Metadata-Version: 2.1
Name: polywrap-wasm
Version: 0.1.2
Summary: Polywrap Wasm
Author: Cesar
Author-email: cesar@polywrap.io
Requires-Python: >=3.10,<4.0
Classifier: Programming Language :: Python :: 3
Classifier: Programming Language :: Python :: 3.10
Classifier: Programming Language :: Python :: 3.11
Requires-Dist: polywrap-core (==0.1.2)
Requires-Dist: polywrap-manifest (==0.1.2)
Requires-Dist: polywrap-msgpack (==0.1.2)
Requires-Dist: wasmtime (>=9.0.0,<10.0.0)
